Workbook

Sheet Dashboard
A1: ECON 114 Study OS — Updated for Units 1 + 2 + 3
A3: KPI | B3: Value | H3: Colour sequence | I3: Use section colours in this order
A4: Topics total | B4: =COUNTA('Study Tracker'!$A$4:$A$200) -> 37 | H4: 1 | I4: Purple
A5: Topics done | B5: =COUNTIF('Study Tracker'!$E$4:$E$200,"Done") -> 0 | H5: 2 | I5: Dark Blue
A6: Completion % | B6: =IF(B4=0,0,B5/B4) -> 0 | H6: 3 | I6: Light Blue
A7: Avg confidence | B7: =IFERROR(AVERAGE('Study Tracker'!$F$4:$F$200),0) -> 1 | H7: 4 | I7: Dark Green
H8: 5 | I8: Pastel Green
H9: 6 | I9: Pastel Yellow
A10: Unit | B10: Total topics | C10: Done | D10: Completion % | E10: Avg confidence | F10: Priority topics left | H10: 7 | I10: Orange
A11: Unit 1 | B11: =COUNTIF('Study Tracker'!$B$4:$B$200,A11) -> 10 | C11: =COUNTIFS('Study Tracker'!$B$4:$B$200,A11,'Study Tracker'!$E$4:$E$200,"Done") -> 0 | D11: =IF(B11=0,0,C11/B11) -> 0 | E11: =IFERROR(AVERAGEIF('Study Tracker'!$B$4:$B$200,A11,'Study Tracker'!$F$4:$F$200),0) -> 1 | F11: =COUNTIFS('Study Tracker'!$B$4:$B$200,A11,'Study Tracker'!$E$4:$E$200,"<>Done",'Study Tracker'!$G$4:$G$200,"Critical")+COUNTIFS('Study Tracker'!$B$4:$B$200,A11,'Study Tracker'!$E$4:$E$200,"<>Done",'Study Tracker'!$G$4:$G$200,"High") -> 10 | H11: 8 | I11: Red
A12: Unit 2 | B12: =COUNTIF('Study Tracker'!$B$4:$B$200,A12) -> 12 | C12: =COUNTIFS('Study Tracker'!$B$4:$B$200,A12,'Study Tracker'!$E$4:$E$200,"Done") -> 0 | D12: =IF(B12=0,0,C12/B12) -> 0 | E12: =IFERROR(AVERAGEIF('Study Tracker'!$B$4:$B$200,A12,'Study Tracker'!$F$4:$F$200),0) -> 1 | F12: =COUNTIFS('Study Tracker'!$B$4:$B$200,A12,'Study Tracker'!$E$4:$E$200,"<>Done",'Study Tracker'!$G$4:$G$200,"Critical")+COUNTIFS('Study Tracker'!$B$4:$B$200,A12,'Study Tracker'!$E$4:$E$200,"<>Done",'Study Tracker'!$G$4:$G$200,"High") -> 11 | H12: 9 | I12: Pink
A13: Unit 3 | B13: =COUNTIF('Study Tracker'!$B$4:$B$200,A13) -> 15 | C13: =COUNTIFS('Study Tracker'!$B$4:$B$200,A13,'Study Tracker'!$E$4:$E$200,"Done") -> 0 | D13: =IF(B13=0,0,C13/B13) -> 0 | E13: =IFERROR(AVERAGEIF('Study Tracker'!$B$4:$B$200,A13,'Study Tracker'!$F$4:$F$200),0) -> 1 | F13: =COUNTIFS('Study Tracker'!$B$4:$B$200,A13,'Study Tracker'!$E$4:$E$200,"<>Done",'Study Tracker'!$G$4:$G$200,"Critical")+COUNTIFS('Study Tracker'!$B$4:$B$200,A13,'Study Tracker'!$E$4:$E$200,"<>Done",'Study Tracker'!$G$4:$G$200,"High") -> 14 | H13: Template intent | I13: Build the same structure for every unit
A14: Unit 4 | B14: =COUNTIF('Study Tracker'!$B$4:$B$200,A14) -> 0 | C14: =COUNTIFS('Study Tracker'!$B$4:$B$200,A14,'Study Tracker'!$E$4:$E$200,"Done") -> 0 | D14: =IF(B14=0,0,C14/B14) -> 0 | E14: =IFERROR(AVERAGEIF('Study Tracker'!$B$4:$B$200,A14,'Study Tracker'!$F$4:$F$200),0) -> 0 | F14: =COUNTIFS('Study Tracker'!$B$4:$B$200,A14,'Study Tracker'!$E$4:$E$200,"<>Done",'Study Tracker'!$G$4:$G$200,"Critical")+COUNTIFS('Study Tracker'!$B$4:$B$200,A14,'Study Tracker'!$E$4:$E$200,"<>Done",'Study Tracker'!$G$4:$G$200,"High") -> 0 | H14: Actual graphs in notes
A15: Unit 5 | B15: =COUNTIF('Study Tracker'!$B$4:$B$200,A15) -> 0 | C15: =COUNTIFS('Study Tracker'!$B$4:$B$200,A15,'Study Tracker'!$E$4:$E$200,"Done") -> 0 | D15: =IF(B15=0,0,C15/B15) -> 0 | E15: =IFERROR(AVERAGEIF('Study Tracker'!$B$4:$B$200,A15,'Study Tracker'!$F$4:$F$200),0) -> 0 | F15: =COUNTIFS('Study Tracker'!$B$4:$B$200,A15,'Study Tracker'!$E$4:$E$200,"<>Done",'Study Tracker'!$G$4:$G$200,"Critical")+COUNTIFS('Study Tracker'!$B$4:$B$200,A15,'Study Tracker'!$E$4:$E$200,"<>Done",'Study Tracker'!$G$4:$G$200,"High") -> 0 | H15: Teach-back tracking

Sheet Unit Planner
A1: Unit Planner — master map for each MegaPack (Units 1–3 live)
A3: Unit | B3: Order | C3: Section type | D3: Section / page block | E3: Subtopic | F3: Source | G3: Exam weight | H3: Need graph? | I3: Need worked answer? | J3: Notes
A4: Unit 1 | B4: 1 | C4: Cover + quick map | D4: Cover + build-up | E4: Title, scope, vocabulary | F4: Slides + assessment | G4: High | H4: No | I4: No | J4: Template row
A5: Unit 1 | B5: 2 | C5: Quick recall | D5: Quick recall | E5: Definitions + big claims | F5: Textbook + slides | G5: High | H5: No | I5: Yes | J5: Template row
A6: Unit 1 | B6: 3 | C6: Core concepts | D6: Full theory | E6: Growth, inequality, capitalism, biosphere | F6: Textbook + slides | G6: High | H6: No | I6: Yes | J6: Template row
A7: Unit 1 | B7: 4 | C7: Graphs + intuition | D7: Actual graph gallery | E7: Hockey stick, inequality, APL, Malthus, biodiversity | F7: Slides + textbook | G7: High | H7: Yes | I7: Yes | J7: Template row
A8: Unit 1 | B8: 5 | C8: Exam toolkit | D8: Exam page | E8: Tutorial logic + negative marking | F8: Tutorial + scope | G8: High | H8: No | I8: Yes | J8: Template row
A9: Unit 2 | B9: 1 | C9: Cover + quick map | D9: Cover + build-up | E9: Title, themes, vocabulary | F9: Slides + textbook | G9: High | H9: No
A10: Unit 2 | B10: 2 | C10: Quick recall | D10: Quick recall | E10: Opportunity cost, rent, trade | F10: Slides + textbook | G10: High | H10: No
A11: Unit 2 | B11: 3 | C11: Core concepts | D11: Full theory | E11: Kutesmart, relative prices, Industrial Revolution | F11: Textbook + slides | G11: High | H11: No
A12: Unit 2 | B12: 4 | C12: Graphs + intuition | D12: Actual graph gallery | E12: History, population, rent, technology choice, wages, CO2 | F12: Slides + textbook | G12: High | H12: Yes
A13: Unit 2 | B13: 5 | C13: Exam toolkit | D13: Exam page | E13: Definition traps + graph traps | F13: Slides + textbook | G13: High | H13: No
A14: Unit 3 | B14: 1 | C14: Cover + quick map | D14: Cover + build-up | E14: Title, concepts, notation | F14: Slides + assessment | G14: High | H14: No | I14: No | J14: Primary-study version
A15: Unit 3 | B15: 2 | C15: Quick recall | D15: Quick recall | E15: Scarcity, utility, MRS, MRT | F15: Slides | G15: High | H15: No | I15: Yes | J15: Use as memorisation map
A16: Unit 3 | B16: 3 | C16: Core concepts | D16: Full theory | E16: Preferences, indifference curves, budget line, optimum | F16: Slides + tutorial | G16: High | H16: No | I16: Yes | J16: Written out more fully
A17: Unit 3 | B17: 4 | C17: Graphs + intuition | D17: Actual graph gallery | E17: ICs, budget line, feasible set, hours worked, inequality | F17: Slides | G17: High | H17: Yes | I17: Yes | J17: Actual graph pages embedded
A18: Unit 3 | B18: 5 | C18: Exam toolkit | D18: Exam page | E18: Income vs substitution, T/F traps, worked answers | F18: Tutorial 3 + scope | G18: High | H18: No | I18: Yes | J18: Negative-marking safe

Sheet Study Tracker
A1: Study Tracker — topic-by-topic progress (Units 1–3 built)
A3: Topic ID | B3: Unit | C3: Section colour | D3: Topic / subtopic | E3: Status | F3: Confidence (1-5) | G3: Priority | H3: Source | I3: Paper notes done? | J3: Teach-back done? | K3: Need revisit? | L3: Comments
A4: U1-01 | B4: Unit 1 | C4: Purple | D4: GDP, GDP per capita, PPP | E4: Reading | F4: 1 | G4: Critical | H4: Slides + textbook | I4: Yes | J4: No | K4: Yes | L4: Template starter row
A5: U1-02 | B5: Unit 1 | C5: Dark Blue | D5: History's hockey stick | E5: Reading | F5: 1 | G5: Critical | H5: Slides + textbook | I5: No | J5: No | K5: Yes | L5: Template starter row
A6: U1-03 | B6: Unit 1 | C6: Light Blue | D6: Between-country inequality | E6: Reading | F6: 1 | G6: High | H6: Slides | I6: No | J6: No | K6: Yes | L6: Template starter row
A7: U1-04 | B7: Unit 1 | C7: Light Blue | D7: Within-country inequality | E7: Reading | F7: 1 | G7: High | H7: Slides
A8: U1-05 | B8: Unit 1 | C8: Dark Green | D8: Diminishing APL | E8: Reading | F8: 1 | G8: Critical | H8: Textbook
A9: U1-06 | B9: Unit 1 | C9: Dark Green | D9: Malthusian equilibrium | E9: Not started | F9: 1 | G9: Critical | H9: Textbook + graph
A10: U1-07 | B10: Unit 1 | C10: Pastel Green | D10: Technology improvement in Malthus model | E10: Not started | F10: 1 | G10: High | H10: Textbook + graph
A11: U1-08 | B11: Unit 1 | C11: Pastel Yellow | D11: Capitalism: private property + firms + markets | E11: Not started | F11: 1 | G11: Critical | H11: Textbook
A12: U1-09 | B12: Unit 1 | C12: Orange | D12: Tutorial 1 logic | E12: Not started | F12: 1 | G12: High | H12: Tutorial
A13: U1-10 | B13: Unit 1 | C13: Pink | D13: Teach-back mastery | E13: Not started | F13: 1 | G13: Critical | H13: MegaPack
A14: U2-01 | B14: Unit 2 | C14: Purple | D14: Kutesmart story | E14: Not started | F14: 1 | G14: Critical | H14: Textbook
A15: U2-02 | B15: Unit 2 | C15: Dark Blue | D15: Opportunity cost | E15: Not started | F15: 1 | G15: Critical | H15: Slides
A16: U2-03 | B16: Unit 2 | C16: Dark Blue | D16: Reservation option | E16: Not started | F16: 1 | G16: High | H16: Slides
A17: U2-04 | B17: Unit 2 | C17: Dark Blue | D17: Economic rent | E17: Not started | F17: 1 | G17: Critical | H17: Slides
A18: U2-05 | B18: Unit 2 | C18: Light Blue | D18: Innovation rent | E18: Not started | F18: 1 | G18: High | H18: Slides
... A25: U2-12 | B25: Unit 2 | C25: Pink | D25: Teach-back mastery | E25: Not started | F25: 1 | G25: Critical | H25: MegaPack
A26: U3-01 | B26: Unit 3 | C26: Purple | D26: Decision-making under scarcity | E26: Not started | F26: 1 | G26: Critical | H26: Slides | I26: No | J26: No | K26: Yes | L26: Start with the model frame
A27: U3-02 | B27: Unit 3 | C27: Purple | D27: Preferences + utility | E27: Not started | F27: 1 | G27: Critical | H27: Slides | I27: No | J27: No | K27: Yes | L27: Define clearly
A28: U3-03 | B28: Unit 3 | C28: Dark Blue | D28: Indifference curves | E28: Not started | F28: 1 | G28: Critical | H28: Slides + graph | I28: No | J28: No | K28: Yes | L28: Properties + interpretation
A29: U3-04 | B29: Unit 3 | C29: Dark Blue | D29: Marginal rate of substitution (MRS) | E29: Not started | F29: 1 | G29: Critical | H29: Slides | I29: No | J29: No | K29: Yes | L29: Willingness to trade
A30: U3-05 | B30: Unit 3 | C30: Light Blue | D30: Budget line equation + intercepts | E30: Not started | F30: 1 | G30: Critical | H30: Slides + graph | I30: No | J30: No | K30: Yes | L30: Relative price + opportunity cost
A31: U3-06 | B31: Unit 3 | C31: Light Blue | D31: Marginal rate of transformation (MRT) | E31: Not started | F31: 1 | G31: High | H31: Slides | I31: No | J31: No | K31: Yes | L31: Constraint trade-off
A32: U3-07 | B32: Unit 3 | C32: Dark Green | D32: Optimal consumer choice | E32: Not started | F32: 1 | G32: Critical | H32: Slides + graph | I32: No | J32: No | K32: Yes | L32: Highest attainable IC
A33: U3-08 | B33: Unit 3 | C33: Dark Green | D33: MRS = MRT at optimum | E33: Not started | F33: 1 | G33: Critical | H33: Slides | I33: No | J33: No | K33: Yes | L33: Exam wording
A34: U3-09 | B34: Unit 3 | C34: Pastel Green | D34: Income effect | E34: Not started | F34: 1 | G34: Critical | H34: Slides + tutorial | I34: No | J34: No | K34: Yes | L34: Goods example
A35: U3-10 | B35: Unit 3 | C35: Pastel Green | D35: Substitution effect | E35: Not started | F35: 1 | G35: Critical | H35: Slides + tutorial | I35: No | J35: No | K35: Yes | L35: Goods example
A36: U3-11 | B36: Unit 3 | C36: Pastel Yellow | D36: Normal vs inferior goods | E36: Not started | F36: 1 | G36: Medium | H36: Slides + scan | I36: No | J36: No | K36: Yes | L36: Edge case
A37: U3-12 | B37: Unit 3 | C37: Pastel Yellow | D37: Working hours and free time | E37: Not started | F37: 1 | G37: Critical | H37: Slides | I37: No | J37: No | K37: Yes | L37: 24-hour budget
... A40: U3-15 | B40: Unit 3 | C40: Pink | D40: Tutorial 3 logic + teach-back mastery | E40: Not started | F40: 1 | G40: Critical | H40: Tutorial 3 + MegaPack | I40: No | J40: No | K40: Yes | L40: Explain Lando vs Oscar aloud

Sheet Session Log
A1: Session Log — use after each Unit 1 or Unit 2 study session
A3: Date | B3: Unit | C3: Topic | D3: Method | E3: Minutes | F3: Could explain twice? | G3: Could teach someone else? | H3: Confidence after | I3: Next action | J3: Reflection
A4: 46112 | B4: Unit 1 | C4: Template topic | D4: Read + paper notes | E4: 45 | F4: No | G4: No | H4: 2 | I4: Repeat tomorrow | J4: Starter template row
A5: 46113 | B5: Unit 1 | C5: Template topic | D5: Teach-back | E5: 30 | F5: Yes | G5: No | H5: 3 | I5: Do again aloud | J5: Starter template row
A6: 46114 | B6: Unit 1 | C6: GDP, GDP per capita, PPP | D6: Read + paper notes | E6: 90 | F6: No | G6: No | H6: 2 | I6: Read out loud and explain.

Sheet Exam Toolkit
A1: Exam Toolkit — built-in answering frameworks
A3: Type | B3: Rule | E3: MCQ ELIMINATION
A4: T/F | B4: Because of negative marking, only answer when you can defend the statement against your notes. | E4: 1 | F4: Eliminate definitions that are too broad
A5: MCQ | B5: Kill wrong answers first. Then justify the survivor with a definition, graph, or model. | E5: 2 | F5: Test graph logic before wording
A6: Graph question | B6: State axes → describe pattern → explain mechanism → conclude why it matters. | E6: 3 | F6: Compare the most precise option
A7: Descriptive | B7: Definition → mechanism → graph/model → result → caution/condition. | E7: 4 | F7: Use tutorial wording as calibration
A8: Teach-back | B8: If you cannot explain it aloud, you do not know it yet. | E8: 5 | F8: If two seem right, one is usually less complete
A9: Tracker rule | B9: Move from Reading → Active recall → Teach-back → Revision → Done.
A11: GRAPH CHECKLIST | E11: DESCRIPTIVE ANSWER FRAME
A12: 1 | B12: Name both axes | E12: 1 | F12: Define the concept
A13: 2 | B13: State what moves and what stays fixed | E13: 2 | F13: State the mechanism
A14: 3 | B14: Explain why the curve slopes that way | E14: 3 | F14: Apply it to the model / graph
A15: 4 | B15: Link the graph to the economic story | E15: 4 | F15: Add one implication or limitation
A16: 5 | B16: State the equilibrium / predicted effect | E16: 5 | F16: Conclude in exam wording

Sheet Template Guide
A1: ECON 114 MegaPack System Template — How to Use
A3: Component | B3: Purpose
A4: Dashboard | B4: Big-picture progress + completion + confidence + readiness
A5: Unit Planner | B5: Master list of note sections and subtopics per unit
A6: Study Tracker | B6: Granular progress by topic, status, confidence, and source
A7: Session Log | B7: Track active recall / teach-back study sessions
A8: Exam Toolkit | B8: Built-in answer frameworks and checklists
A9: Colour sequence | B9: Purple → Dark Blue → Light Blue → Dark Green → Pastel Green → Pastel Yellow → Orange → Red → Pink
A10: Template use | B10: Duplicate rows for Unit 1 first, then Units 2–5 later
A11: Rule | B11: Only populate from your uploaded textbook, slides, tutorials, and assessment scope
A12: Best workflow | B12: Read → paper notes → self-explain twice → teach another person → mark confidence

Sheet Lists
A1: Status | B1: Confidence | C1: Priority | D1: Resource
A2: Not started | B2: 1 | C2: Critical | D2: Textbook
A3: Reading | B3: 2 | C3: High | D3: Slides
A4: Active recall | B4: 3 | C4: Medium | D4: Tutorial
A5: Teach-back | B5: 4 | C5: Low | D5: Graph
A6: Past paper | B6: 5 | C6: Parking Lot | D6: Own notes
A7: Revision
A8: Done
A9: Stuck
